rtl/ram_init.v
module ram_init
(
  clk_i, addr_i, data_o
);

  localparam CACHE_LINE   = 128;
  localparam CACHE_DEPTH  = 32;
  localparam DATA_WIDTH   = 32;
  localparam ADDR_WIDTH   = $clog2(CACHE_DEPTH);
  localparam N_DATA_LINE  = CACHE_LINE / DATA_WIDTH;

  input                         clk_i;
  input       [ADDR_WIDTH-1:0]  addr_i;
  output reg  [CACHE_LINE-1:0]  data_o;

  integer i, j;

  reg [CACHE_LINE-1:0]  cache_mem [CACHE_DEPTH-1:0];

  initial begin
    for(i=0; i<CACHE_DEPTH; i=i+1) begin
      for(j=0; j<N_DATA_LINE; j=j+1) begin
        cache_mem[i][(j*DATA_WIDTH)+:DATA_WIDTH] = (i*N_DATA_LINE) + j;
      end
    end
  end

  always @ (posedge clk_i) begin
    data_o  <= cache_mem[addr_i];
  end

endmodule // ram_init

tb/tb_ram_init.v
module tb_ram_init ();

  /* local parameters */
  localparam CACHE_LINE   = 128;
  localparam CACHE_DEPTH  = 32;
  localparam ADDR_WIDTH   = $clog2(CACHE_DEPTH);

  /* sim regs n wires */
  reg                     clk_i;
  reg   [ADDR_WIDTH-1:0]  addr_i;
  wire  [CACHE_LINE-1:0]  data_o;

  /* integers */
  integer i;

  /* initial values */
  initial begin
    clk_i   = 0;
    addr_i  = 0;
    $dumpfile("ram_init.vcd");
    $dumpvars();
    for(i=0; i<CACHE_DEPTH; i=i+1) $dumpvars(1, dut.cache_mem[i]);
    #1000 $finish;
  end

  /* clock */
  always begin
    #1  clk_i = ~clk_i;
  end

  /* simulation */
  always @ (negedge clk_i) begin
    addr_i  <=  addr_i + 1;
  end

  /* dut */
  ram_init
    dut (
        .clk_i  (clk_i),
        .addr_i (addr_i),
        .data_o (data_o)
      );

endmodule // tb_ram_init

build/ram_init.vcd
$date
	Tue Feb 11 06:41:13 2020
$end
$version
	Icarus Verilog
$end
$timescale
	1s
$end
$scope module tb_ram_init $end
$var wire 128 ! data_o [127:0] $end
$var reg 5 " addr_i [4:0] $end
$var reg 1 # clk_i $end
$var integer 32 $ i [31:0] $end
$scope module dut $end
$var wire 5 % addr_i [4:0] $end
$var wire 1 # clk_i $end
$var reg 128 & data_o [127:0] $end
$var integer 32 ' i [31:0] $end
$var integer 32 ( j [31:0] $end
$upscope $end
$upscope $end
$scope module tb_ram_init $end
$scope module dut $end
$var reg 128 ) \cache_mem[0] [127:0] $end
$upscope $end
$upscope $end
$scope module tb_ram_init $end
$scope module dut $end
$var reg 128 * \cache_mem[1] [127:0] $end
$upscope $end
$upscope $end
$scope module tb_ram_init $end
$scope module dut $end
$var reg 128 + \cache_mem[2] [127:0] $end
$upscope $end
$upscope $end
$scope module tb_ram_init $end
$scope module dut $end
$var reg 128 , \cache_mem[3] [127:0] $end
$upscope $end
$upscope $end
$scope module tb_ram_init $end
$scope module dut $end
$var reg 128 - \cache_mem[4] [127:0] $end
$upscope $end
$upscope $end
$scope module tb_ram_init $end
$scope module dut $end
$var reg 128 . \cache_mem[5] [127:0] $end
$upscope $end
$upscope $end
$scope module tb_ram_init $end
$scope module dut $end
$var reg 128 / \cache_mem[6] [127:0] $end
$upscope $end
$upscope $end
$scope module tb_ram_init $end
$scope module dut $end
$var reg 128 0 \cache_mem[7] [127:0] $end
$upscope $end
$upscope $end
$scope module tb_ram_init $end
$scope module dut $end
$var reg 128 1 \cache_mem[8] [127:0] $end
$upscope $end
$upscope $end
$scope module tb_ram_init $end
$scope module dut $end
$var reg 128 2 \cache_mem[9] [127:0] $end
$upscope $end
$upscope $end
$scope module tb_ram_init $end
$scope module dut $end
$var reg 128 3 \cache_mem[10] [127:0] $end
$upscope $end
$upscope $end
$scope module tb_ram_init $end
$scope module dut $end
$var reg 128 4 \cache_mem[11] [127:0] $end
$upscope $end
$upscope $end
$scope module tb_ram_init $end
$scope module dut $end
$var reg 128 5 \cache_mem[12] [127:0] $end
$upscope $end
$upscope $end
$scope module tb_ram_init $end
$scope module dut $end
$var reg 128 6 \cache_mem[13] [127:0] $end
$upscope $end
$upscope $end
$scope module tb_ram_init $end
$scope module dut $end
$var reg 128 7 \cache_mem[14] [127:0] $end
$upscope $end
$upscope $end
$scope module tb_ram_init $end
$scope module dut $end
$var reg 128 8 \cache_mem[15] [127:0] $end
$upscope $end
$upscope $end
$scope module tb_ram_init $end
$scope module dut $end
$var reg 128 9 \cache_mem[16] [127:0] $end
$upscope $end
$upscope $end
$scope module tb_ram_init $end
$scope module dut $end
$var reg 128 : \cache_mem[17] [127:0] $end
$upscope $end
$upscope $end
$scope module tb_ram_init $end
$scope module dut $end
$var reg 128 ; \cache_mem[18] [127:0] $end
$upscope $end
$upscope $end
$scope module tb_ram_init $end
$scope module dut $end
$var reg 128 < \cache_mem[19] [127:0] $end
$upscope $end
$upscope $end
$scope module tb_ram_init $end
$scope module dut $end
$var reg 128 = \cache_mem[20] [127:0] $end
$upscope $end
$upscope $end
$scope module tb_ram_init $end
$scope module dut $end
$var reg 128 > \cache_mem[21] [127:0] $end
$upscope $end
$upscope $end
$scope module tb_ram_init $end
$scope module dut $end
$var reg 128 ? \cache_mem[22] [127:0] $end
$upscope $end
$upscope $end
$scope module tb_ram_init $end
$scope module dut $end
$var reg 128 @ \cache_mem[23] [127:0] $end
$upscope $end
$upscope $end
$scope module tb_ram_init $end
$scope module dut $end
$var reg 128 A \cache_mem[24] [127:0] $end
$upscope $end
$upscope $end
$scope module tb_ram_init $end
$scope module dut $end
$var reg 128 B \cache_mem[25] [127:0] $end
$upscope $end
$upscope $end
$scope module tb_ram_init $end
$scope module dut $end
$var reg 128 C \cache_mem[26] [127:0] $end
$upscope $end
$upscope $end
$scope module tb_ram_init $end
$scope module dut $end
$var reg 128 D \cache_mem[27] [127:0] $end
$upscope $end
$upscope $end
$scope module tb_ram_init $end
$scope module dut $end
$var reg 128 E \cache_mem[28] [127:0] $end
$upscope $end
$upscope $end
$scope module tb_ram_init $end
$scope module dut $end
$var reg 128 F \cache_mem[29] [127:0] $end
$upscope $end
$upscope $end
$scope module tb_ram_init $end
$scope module dut $end
$var reg 128 G \cache_mem[30] [127:0] $end
$upscope $end
$upscope $end
$scope module tb_ram_init $end
$scope module dut $end
$var reg 128 H \cache_mem[31] [127:0] $end
$upscope $end
$upscope $end
$enddefinitions $end
#0
$dumpvars
b1111111000000000000000000000000011111100000000000000000000000000111110100000000000000000000000001111100 H
b1111011000000000000000000000000011110100000000000000000000000000111100100000000000000000000000001111000 G
b1110111000000000000000000000000011101100000000000000000000000000111010100000000000000000000000001110100 F
b1110011000000000000000000000000011100100000000000000000000000000111000100000000000000000000000001110000 E
b1101111000000000000000000000000011011100000000000000000000000000110110100000000000000000000000001101100 D
b1101011000000000000000000000000011010100000000000000000000000000110100100000000000000000000000001101000 C
b1100111000000000000000000000000011001100000000000000000000000000110010100000000000000000000000001100100 B
b1100011000000000000000000000000011000100000000000000000000000000110000100000000000000000000000001100000 A
b1011111000000000000000000000000010111100000000000000000000000000101110100000000000000000000000001011100 @
b1011011000000000000000000000000010110100000000000000000000000000101100100000000000000000000000001011000 ?
b1010111000000000000000000000000010101100000000000000000000000000101010100000000000000000000000001010100 >
b1010011000000000000000000000000010100100000000000000000000000000101000100000000000000000000000001010000 =
b1001111000000000000000000000000010011100000000000000000000000000100110100000000000000000000000001001100 <
b1001011000000000000000000000000010010100000000000000000000000000100100100000000000000000000000001001000 ;
b1000111000000000000000000000000010001100000000000000000000000000100010100000000000000000000000001000100 :
b1000011000000000000000000000000010000100000000000000000000000000100000100000000000000000000000001000000 9
b111111000000000000000000000000001111100000000000000000000000000011110100000000000000000000000000111100 8
b111011000000000000000000000000001110100000000000000000000000000011100100000000000000000000000000111000 7
b110111000000000000000000000000001101100000000000000000000000000011010100000000000000000000000000110100 6
b110011000000000000000000000000001100100000000000000000000000000011000100000000000000000000000000110000 5
b101111000000000000000000000000001011100000000000000000000000000010110100000000000000000000000000101100 4
b101011000000000000000000000000001010100000000000000000000000000010100100000000000000000000000000101000 3
b100111000000000000000000000000001001100000000000000000000000000010010100000000000000000000000000100100 2
b100011000000000000000000000000001000100000000000000000000000000010000100000000000000000000000000100000 1
b11111000000000000000000000000000111100000000000000000000000000001110100000000000000000000000000011100 0
b11011000000000000000000000000000110100000000000000000000000000001100100000000000000000000000000011000 /
b10111000000000000000000000000000101100000000000000000000000000001010100000000000000000000000000010100 .
b10011000000000000000000000000000100100000000000000000000000000001000100000000000000000000000000010000 -
b1111000000000000000000000000000011100000000000000000000000000000110100000000000000000000000000001100 ,
b1011000000000000000000000000000010100000000000000000000000000000100100000000000000000000000000001000 +
b111000000000000000000000000000001100000000000000000000000000000010100000000000000000000000000000100 *
b11000000000000000000000000000000100000000000000000000000000000000100000000000000000000000000000000 )
b100 (
b100000 '
bx &
b0 %
b100000 $
0#
b0 "
bx !
$end
#1
b11000000000000000000000000000000100000000000000000000000000000000100000000000000000000000000000000 !
b11000000000000000000000000000000100000000000000000000000000000000100000000000000000000000000000000 &
1#
#2
b1 "
b1 %
0#
#3
b111000000000000000000000000000001100000000000000000000000000000010100000000000000000000000000000100 !
b111000000000000000000000000000001100000000000000000000000000000010100000000000000000000000000000100 &
1#
#4
b10 "
b10 %
0#
#5
b1011000000000000000000000000000010100000000000000000000000000000100100000000000000000000000000001000 !
b1011000000000000000000000000000010100000000000000000000000000000100100000000000000000000000000001000 &
1#
#6
b11 "
b11 %
0#
#7
b1111000000000000000000000000000011100000000000000000000000000000110100000000000000000000000000001100 !
b1111000000000000000000000000000011100000000000000000000000000000110100000000000000000000000000001100 &
1#
#8
b100 "
b100 %
0#
#9
b10011000000000000000000000000000100100000000000000000000000000001000100000000000000000000000000010000 !
b10011000000000000000000000000000100100000000000000000000000000001000100000000000000000000000000010000 &
1#
#10
b101 "
b101 %
0#
#11
b10111000000000000000000000000000101100000000000000000000000000001010100000000000000000000000000010100 !
b10111000000000000000000000000000101100000000000000000000000000001010100000000000000000000000000010100 &
1#
#12
b110 "
b110 %
0#
#13
b11011000000000000000000000000000110100000000000000000000000000001100100000000000000000000000000011000 !
b11011000000000000000000000000000110100000000000000000000000000001100100000000000000000000000000011000 &
1#
#14
b111 "
b111 %
0#
#15
b11111000000000000000000000000000111100000000000000000000000000001110100000000000000000000000000011100 !
b11111000000000000000000000000000111100000000000000000000000000001110100000000000000000000000000011100 &
1#
#16
b1000 "
b1000 %
0#
#17
b100011000000000000000000000000001000100000000000000000000000000010000100000000000000000000000000100000 !
b100011000000000000000000000000001000100000000000000000000000000010000100000000000000000000000000100000 &
1#
#18
b1001 "
b1001 %
0#
#19
b100111000000000000000000000000001001100000000000000000000000000010010100000000000000000000000000100100 !
b100111000000000000000000000000001001100000000000000000000000000010010100000000000000000000000000100100 &
1#
#20
b1010 "
b1010 %
0#
#21
b101011000000000000000000000000001010100000000000000000000000000010100100000000000000000000000000101000 !
b101011000000000000000000000000001010100000000000000000000000000010100100000000000000000000000000101000 &
1#
#22
b1011 "
b1011 %
0#
#23
b101111000000000000000000000000001011100000000000000000000000000010110100000000000000000000000000101100 !
b101111000000000000000000000000001011100000000000000000000000000010110100000000000000000000000000101100 &
1#
#24
b1100 "
b1100 %
0#
#25
b110011000000000000000000000000001100100000000000000000000000000011000100000000000000000000000000110000 !
b110011000000000000000000000000001100100000000000000000000000000011000100000000000000000000000000110000 &
1#
#26
b1101 "
b1101 %
0#
#27
b110111000000000000000000000000001101100000000000000000000000000011010100000000000000000000000000110100 !
b110111000000000000000000000000001101100000000000000000000000000011010100000000000000000000000000110100 &
1#
#28
b1110 "
b1110 %
0#
#29
b111011000000000000000000000000001110100000000000000000000000000011100100000000000000000000000000111000 !
b111011000000000000000000000000001110100000000000000000000000000011100100000000000000000000000000111000 &
1#
#30
b1111 "
b1111 %
0#
#31
b111111000000000000000000000000001111100000000000000000000000000011110100000000000000000000000000111100 !
b111111000000000000000000000000001111100000000000000000000000000011110100000000000000000000000000111100 &
1#
#32
b10000 "
b10000 %
0#
#33
b1000011000000000000000000000000010000100000000000000000000000000100000100000000000000000000000001000000 !
b1000011000000000000000000000000010000100000000000000000000000000100000100000000000000000000000001000000 &
1#
#34
b10001 "
b10001 %
0#
#35
b1000111000000000000000000000000010001100000000000000000000000000100010100000000000000000000000001000100 !
b1000111000000000000000000000000010001100000000000000000000000000100010100000000000000000000000001000100 &
1#
#36
b10010 "
b10010 %
0#
#37
b1001011000000000000000000000000010010100000000000000000000000000100100100000000000000000000000001001000 !
b1001011000000000000000000000000010010100000000000000000000000000100100100000000000000000000000001001000 &
1#
#38
b10011 "
b10011 %
0#
#39
b1001111000000000000000000000000010011100000000000000000000000000100110100000000000000000000000001001100 !
b1001111000000000000000000000000010011100000000000000000000000000100110100000000000000000000000001001100 &
1#
#40
b10100 "
b10100 %
0#
#41
b1010011000000000000000000000000010100100000000000000000000000000101000100000000000000000000000001010000 !
b1010011000000000000000000000000010100100000000000000000000000000101000100000000000000000000000001010000 &
1#
#42
b10101 "
b10101 %
0#
#43
b1010111000000000000000000000000010101100000000000000000000000000101010100000000000000000000000001010100 !
b1010111000000000000000000000000010101100000000000000000000000000101010100000000000000000000000001010100 &
1#
#44
b10110 "
b10110 %
0#
#45
b1011011000000000000000000000000010110100000000000000000000000000101100100000000000000000000000001011000 !
b1011011000000000000000000000000010110100000000000000000000000000101100100000000000000000000000001011000 &
1#
#46
b10111 "
b10111 %
0#
#47
b1011111000000000000000000000000010111100000000000000000000000000101110100000000000000000000000001011100 !
b1011111000000000000000000000000010111100000000000000000000000000101110100000000000000000000000001011100 &
1#
#48
b11000 "
b11000 %
0#
#49
b1100011000000000000000000000000011000100000000000000000000000000110000100000000000000000000000001100000 !
b1100011000000000000000000000000011000100000000000000000000000000110000100000000000000000000000001100000 &
1#
#50
b11001 "
b11001 %
0#
#51
b1100111000000000000000000000000011001100000000000000000000000000110010100000000000000000000000001100100 !
b1100111000000000000000000000000011001100000000000000000000000000110010100000000000000000000000001100100 &
1#
#52
b11010 "
b11010 %
0#
#53
b1101011000000000000000000000000011010100000000000000000000000000110100100000000000000000000000001101000 !
b1101011000000000000000000000000011010100000000000000000000000000110100100000000000000000000000001101000 &
1#
#54
b11011 "
b11011 %
0#
#55
b1101111000000000000000000000000011011100000000000000000000000000110110100000000000000000000000001101100 !
b1101111000000000000000000000000011011100000000000000000000000000110110100000000000000000000000001101100 &
1#
#56
b11100 "
b11100 %
0#
#57
b1110011000000000000000000000000011100100000000000000000000000000111000100000000000000000000000001110000 !
b1110011000000000000000000000000011100100000000000000000000000000111000100000000000000000000000001110000 &
1#
#58
b11101 "
b11101 %
0#
#59
b1110111000000000000000000000000011101100000000000000000000000000111010100000000000000000000000001110100 !
b1110111000000000000000000000000011101100000000000000000000000000111010100000000000000000000000001110100 &
1#
#60
b11110 "
b11110 %
0#
#61
b1111011000000000000000000000000011110100000000000000000000000000111100100000000000000000000000001111000 !
b1111011000000000000000000000000011110100000000000000000000000000111100100000000000000000000000001111000 &
1#
#62
b11111 "
b11111 %
0#
#63
b1111111000000000000000000000000011111100000000000000000000000000111110100000000000000000000000001111100 !
b1111111000000000000000000000000011111100000000000000000000000000111110100000000000000000000000001111100 &
1#
#64
b0 "
b0 %
0#
#65
b11000000000000000000000000000000100000000000000000000000000000000100000000000000000000000000000000 !
b11000000000000000000000000000000100000000000000000000000000000000100000000000000000000000000000000 &
1#
#66
b1 "
b1 %
0#
#67
b111000000000000000000000000000001100000000000000000000000000000010100000000000000000000000000000100 !
b111000000000000000000000000000001100000000000000000000000000000010100000000000000000000000000000100 &
1#
#68
b10 "
b10 %
0#
#69
b1011000000000000000000000000000010100000000000000000000000000000100100000000000000000000000000001000 !
b1011000000000000000000000000000010100000000000000000000000000000100100000000000000000000000000001000 &
1#
#70
b11 "
b11 %
0#
#71
b1111000000000000000000000000000011100000000000000000000000000000110100000000000000000000000000001100 !
b1111000000000000000000000000000011100000000000000000000000000000110100000000000000000000000000001100 &
1#
#72
b100 "
b100 %
0#
#73
b10011000000000000000000000000000100100000000000000000000000000001000100000000000000000000000000010000 !
b10011000000000000000000000000000100100000000000000000000000000001000100000000000000000000000000010000 &
1#
#74
b101 "
b101 %
0#
#75
b10111000000000000000000000000000101100000000000000000000000000001010100000000000000000000000000010100 !
b10111000000000000000000000000000101100000000000000000000000000001010100000000000000000000000000010100 &
1#
#76
b110 "
b110 %
0#
#77
b11011000000000000000000000000000110100000000000000000000000000001100100000000000000000000000000011000 !
b11011000000000000000000000000000110100000000000000000000000000001100100000000000000000000000000011000 &
1#
#78
b111 "
b111 %
0#
#79
b11111000000000000000000000000000111100000000000000000000000000001110100000000000000000000000000011100 !
b11111000000000000000000000000000111100000000000000000000000000001110100000000000000000000000000011100 &
1#
#80
b1000 "
b1000 %
0#
#81
b100011000000000000000000000000001000100000000000000000000000000010000100000000000000000000000000100000 !
b100011000000000000000000000000001000100000000000000000000000000010000100000000000000000000000000100000 &
1#
#82
b1001 "
b1001 %
0#
#83
b100111000000000000000000000000001001100000000000000000000000000010010100000000000000000000000000100100 !
b100111000000000000000000000000001001100000000000000000000000000010010100000000000000000000000000100100 &
1#
#84
b1010 "
b1010 %
0#
#85
b101011000000000000000000000000001010100000000000000000000000000010100100000000000000000000000000101000 !
b101011000000000000000000000000001010100000000000000000000000000010100100000000000000000000000000101000 &
1#
#86
b1011 "
b1011 %
0#
#87
b101111000000000000000000000000001011100000000000000000000000000010110100000000000000000000000000101100 !
b101111000000000000000000000000001011100000000000000000000000000010110100000000000000000000000000101100 &
1#
#88
b1100 "
b1100 %
0#
#89
b110011000000000000000000000000001100100000000000000000000000000011000100000000000000000000000000110000 !
b110011000000000000000000000000001100100000000000000000000000000011000100000000000000000000000000110000 &
1#
#90
b1101 "
b1101 %
0#
#91
b110111000000000000000000000000001101100000000000000000000000000011010100000000000000000000000000110100 !
b110111000000000000000000000000001101100000000000000000000000000011010100000000000000000000000000110100 &
1#
#92
b1110 "
b1110 %
0#
#93
b111011000000000000000000000000001110100000000000000000000000000011100100000000000000000000000000111000 !
b111011000000000000000000000000001110100000000000000000000000000011100100000000000000000000000000111000 &
1#
#94
b1111 "
b1111 %
0#
#95
b111111000000000000000000000000001111100000000000000000000000000011110100000000000000000000000000111100 !
b111111000000000000000000000000001111100000000000000000000000000011110100000000000000000000000000111100 &
1#
#96
b10000 "
b10000 %
0#
#97
b1000011000000000000000000000000010000100000000000000000000000000100000100000000000000000000000001000000 !
b1000011000000000000000000000000010000100000000000000000000000000100000100000000000000000000000001000000 &
1#
#98
b10001 "
b10001 %
0#
#99
b1000111000000000000000000000000010001100000000000000000000000000100010100000000000000000000000001000100 !
b1000111000000000000000000000000010001100000000000000000000000000100010100000000000000000000000001000100 &
1#
#100
b10010 "
b10010 %
0#
#101
b1001011000000000000000000000000010010100000000000000000000000000100100100000000000000000000000001001000 !
b1001011000000000000000000000000010010100000000000000000000000000100100100000000000000000000000001001000 &
1#
#102
b10011 "
b10011 %
0#
#103
b1001111000000000000000000000000010011100000000000000000000000000100110100000000000000000000000001001100 !
b1001111000000000000000000000000010011100000000000000000000000000100110100000000000000000000000001001100 &
1#
#104
b10100 "
b10100 %
0#
#105
b1010011000000000000000000000000010100100000000000000000000000000101000100000000000000000000000001010000 !
b1010011000000000000000000000000010100100000000000000000000000000101000100000000000000000000000001010000 &
1#
#106
b10101 "
b10101 %
0#
#107
b1010111000000000000000000000000010101100000000000000000000000000101010100000000000000000000000001010100 !
b1010111000000000000000000000000010101100000000000000000000000000101010100000000000000000000000001010100 &
1#
#108
b10110 "
b10110 %
0#
#109
b1011011000000000000000000000000010110100000000000000000000000000101100100000000000000000000000001011000 !
b1011011000000000000000000000000010110100000000000000000000000000101100100000000000000000000000001011000 &
1#
#110
b10111 "
b10111 %
0#
#111
b1011111000000000000000000000000010111100000000000000000000000000101110100000000000000000000000001011100 !
b1011111000000000000000000000000010111100000000000000000000000000101110100000000000000000000000001011100 &
1#
#112
b11000 "
b11000 %
0#
#113
b1100011000000000000000000000000011000100000000000000000000000000110000100000000000000000000000001100000 !
b1100011000000000000000000000000011000100000000000000000000000000110000100000000000000000000000001100000 &
1#
#114
b11001 "
b11001 %
0#
#115
b1100111000000000000000000000000011001100000000000000000000000000110010100000000000000000000000001100100 !
b1100111000000000000000000000000011001100000000000000000000000000110010100000000000000000000000001100100 &
1#
#116
b11010 "
b11010 %
0#
#117
b1101011000000000000000000000000011010100000000000000000000000000110100100000000000000000000000001101000 !
b1101011000000000000000000000000011010100000000000000000000000000110100100000000000000000000000001101000 &
1#
#118
b11011 "
b11011 %
0#
#119
b1101111000000000000000000000000011011100000000000000000000000000110110100000000000000000000000001101100 !
b1101111000000000000000000000000011011100000000000000000000000000110110100000000000000000000000001101100 &
1#
#120
b11100 "
b11100 %
0#
#121
b1110011000000000000000000000000011100100000000000000000000000000111000100000000000000000000000001110000 !
b1110011000000000000000000000000011100100000000000000000000000000111000100000000000000000000000001110000 &
1#
#122
b11101 "
b11101 %
0#
#123
b1110111000000000000000000000000011101100000000000000000000000000111010100000000000000000000000001110100 !
b1110111000000000000000000000000011101100000000000000000000000000111010100000000000000000000000001110100 &
1#
#124
b11110 "
b11110 %
0#
#125
b1111011000000000000000000000000011110100000000000000000000000000111100100000000000000000000000001111000 !
b1111011000000000000000000000000011110100000000000000000000000000111100100000000000000000000000001111000 &
1#
#126
b11111 "
b11111 %
0#
#127
b1111111000000000000000000000000011111100000000000000000000000000111110100000000000000000000000001111100 !
b1111111000000000000000000000000011111100000000000000000000000000111110100000000000000000000000001111100 &
1#
#128
b0 "
b0 %
0#
#129
b11000000000000000000000000000000100000000000000000000000000000000100000000000000000000000000000000 !
b11000000000000000000000000000000100000000000000000000000000000000100000000000000000000000000000000 &
1#
#130
b1 "
b1 %
0#
#131
b111000000000000000000000000000001100000000000000000000000000000010100000000000000000000000000000100 !
b111000000000000000000000000000001100000000000000000000000000000010100000000000000000000000000000100 &
1#
#132
b10 "
b10 %
0#
#133
b1011000000000000000000000000000010100000000000000000000000000000100100000000000000000000000000001000 !
b1011000000000000000000000000000010100000000000000000000000000000100100000000000000000000000000001000 &
1#
#134
b11 "
b11 %
0#
#135
b1111000000000000000000000000000011100000000000000000000000000000110100000000000000000000000000001100 !
b1111000000000000000000000000000011100000000000000000000000000000110100000000000000000000000000001100 &
1#
#136
b100 "
b100 %
0#
#137
b10011000000000000000000000000000100100000000000000000000000000001000100000000000000000000000000010000 !
b10011000000000000000000000000000100100000000000000000000000000001000100000000000000000000000000010000 &
1#
#138
b101 "
b101 %
0#
#139
b10111000000000000000000000000000101100000000000000000000000000001010100000000000000000000000000010100 !
b10111000000000000000000000000000101100000000000000000000000000001010100000000000000000000000000010100 &
1#
#140
b110 "
b110 %
0#
#141
b11011000000000000000000000000000110100000000000000000000000000001100100000000000000000000000000011000 !
b11011000000000000000000000000000110100000000000000000000000000001100100000000000000000000000000011000 &
1#
#142
b111 "
b111 %
0#
#143
b11111000000000000000000000000000111100000000000000000000000000001110100000000000000000000000000011100 !
b11111000000000000000000000000000111100000000000000000000000000001110100000000000000000000000000011100 &
1#
#144
b1000 "
b1000 %
0#
#145
b100011000000000000000000000000001000100000000000000000000000000010000100000000000000000000000000100000 !
b100011000000000000000000000000001000100000000000000000000000000010000100000000000000000000000000100000 &
1#
#146
b1001 "
b1001 %
0#
#147
b100111000000000000000000000000001001100000000000000000000000000010010100000000000000000000000000100100 !
b100111000000000000000000000000001001100000000000000000000000000010010100000000000000000000000000100100 &
1#
#148
b1010 "
b1010 %
0#
#149
b101011000000000000000000000000001010100000000000000000000000000010100100000000000000000000000000101000 !
b101011000000000000000000000000001010100000000000000000000000000010100100000000000000000000000000101000 &
1#
#150
b1011 "
b1011 %
0#
#151
b101111000000000000000000000000001011100000000000000000000000000010110100000000000000000000000000101100 !
b101111000000000000000000000000001011100000000000000000000000000010110100000000000000000000000000101100 &
1#
#152
b1100 "
b1100 %
0#
#153
b110011000000000000000000000000001100100000000000000000000000000011000100000000000000000000000000110000 !
b110011000000000000000000000000001100100000000000000000000000000011000100000000000000000000000000110000 &
1#
#154
b1101 "
b1101 %
0#
#155
b110111000000000000000000000000001101100000000000000000000000000011010100000000000000000000000000110100 !
b110111000000000000000000000000001101100000000000000000000000000011010100000000000000000000000000110100 &
1#
#156
b1110 "
b1110 %
0#
#157
b111011000000000000000000000000001110100000000000000000000000000011100100000000000000000000000000111000 !
b111011000000000000000000000000001110100000000000000000000000000011100100000000000000000000000000111000 &
1#
#158
b1111 "
b1111 %
0#
#159
b111111000000000000000000000000001111100000000000000000000000000011110100000000000000000000000000111100 !
b111111000000000000000000000000001111100000000000000000000000000011110100000000000000000000000000111100 &
1#
#160
b10000 "
b10000 %
0#
#161
b1000011000000000000000000000000010000100000000000000000000000000100000100000000000000000000000001000000 !
b1000011000000000000000000000000010000100000000000000000000000000100000100000000000000000000000001000000 &
1#
#162
b10001 "
b10001 %
0#
#163
b1000111000000000000000000000000010001100000000000000000000000000100010100000000000000000000000001000100 !
b1000111000000000000000000000000010001100000000000000000000000000100010100000000000000000000000001000100 &
1#
#164
b10010 "
b10010 %
0#
#165
b1001011000000000000000000000000010010100000000000000000000000000100100100000000000000000000000001001000 !
b1001011000000000000000000000000010010100000000000000000000000000100100100000000000000000000000001001000 &
1#
#166
b10011 "
b10011 %
0#
#167
b1001111000000000000000000000000010011100000000000000000000000000100110100000000000000000000000001001100 !
b1001111000000000000000000000000010011100000000000000000000000000100110100000000000000000000000001001100 &
1#
#168
b10100 "
b10100 %
0#
#169
b1010011000000000000000000000000010100100000000000000000000000000101000100000000000000000000000001010000 !
b1010011000000000000000000000000010100100000000000000000000000000101000100000000000000000000000001010000 &
1#
#170
b10101 "
b10101 %
0#
#171
b1010111000000000000000000000000010101100000000000000000000000000101010100000000000000000000000001010100 !
b1010111000000000000000000000000010101100000000000000000000000000101010100000000000000000000000001010100 &
1#
#172
b10110 "
b10110 %
0#
#173
b1011011000000000000000000000000010110100000000000000000000000000101100100000000000000000000000001011000 !
b1011011000000000000000000000000010110100000000000000000000000000101100100000000000000000000000001011000 &
1#
#174
b10111 "
b10111 %
0#
#175
b1011111000000000000000000000000010111100000000000000000000000000101110100000000000000000000000001011100 !
b1011111000000000000000000000000010111100000000000000000000000000101110100000000000000000000000001011100 &
1#
#176
b11000 "
b11000 %
0#
#177
b1100011000000000000000000000000011000100000000000000000000000000110000100000000000000000000000001100000 !
b1100011000000000000000000000000011000100000000000000000000000000110000100000000000000000000000001100000 &
1#
#178
b11001 "
b11001 %
0#
#179
b1100111000000000000000000000000011001100000000000000000000000000110010100000000000000000000000001100100 !
b1100111000000000000000000000000011001100000000000000000000000000110010100000000000000000000000001100100 &
1#
#180
b11010 "
b11010 %
0#
#181
b1101011000000000000000000000000011010100000000000000000000000000110100100000000000000000000000001101000 !
b1101011000000000000000000000000011010100000000000000000000000000110100100000000000000000000000001101000 &
1#
#182
b11011 "
b11011 %
0#
#183
b1101111000000000000000000000000011011100000000000000000000000000110110100000000000000000000000001101100 !
b1101111000000000000000000000000011011100000000000000000000000000110110100000000000000000000000001101100 &
1#
#184
b11100 "
b11100 %
0#
#185
b1110011000000000000000000000000011100100000000000000000000000000111000100000000000000000000000001110000 !
b1110011000000000000000000000000011100100000000000000000000000000111000100000000000000000000000001110000 &
1#
#186
b11101 "
b11101 %
0#
#187
b1110111000000000000000000000000011101100000000000000000000000000111010100000000000000000000000001110100 !
b1110111000000000000000000000000011101100000000000000000000000000111010100000000000000000000000001110100 &
1#
#188
b11110 "
b11110 %
0#
#189
b1111011000000000000000000000000011110100000000000000000000000000111100100000000000000000000000001111000 !
b1111011000000000000000000000000011110100000000000000000000000000111100100000000000000000000000001111000 &
1#
#190
b11111 "
b11111 %
0#
#191
b1111111000000000000000000000000011111100000000000000000000000000111110100000000000000000000000001111100 !
b1111111000000000000000000000000011111100000000000000000000000000111110100000000000000000000000001111100 &
1#
#192
b0 "
b0 %
0#
#193
b11000000000000000000000000000000100000000000000000000000000000000100000000000000000000000000000000 !
b11000000000000000000000000000000100000000000000000000000000000000100000000000000000000000000000000 &
1#
#194
b1 "
b1 %
0#
#195
b111000000000000000000000000000001100000000000000000000000000000010100000000000000000000000000000100 !
b111000000000000000000000000000001100000000000000000000000000000010100000000000000000000000000000100 &
1#
#196
b10 "
b10 %
0#
#197
b1011000000000000000000000000000010100000000000000000000000000000100100000000000000000000000000001000 !
b1011000000000000000000000000000010100000000000000000000000000000100100000000000000000000000000001000 &
1#
#198
b11 "
b11 %
0#
#199
b1111000000000000000000000000000011100000000000000000000000000000110100000000000000000000000000001100 !
b1111000000000000000000000000000011100000000000000000000000000000110100000000000000000000000000001100 &
1#
#200
b100 "
b100 %
0#
#201
b10011000000000000000000000000000100100000000000000000000000000001000100000000000000000000000000010000 !
b10011000000000000000000000000000100100000000000000000000000000001000100000000000000000000000000010000 &
1#
#202
b101 "
b101 %
0#
#203
b10111000000000000000000000000000101100000000000000000000000000001010100000000000000000000000000010100 !
b10111000000000000000000000000000101100000000000000000000000000001010100000000000000000000000000010100 &
1#
#204
b110 "
b110 %
0#
#205
b11011000000000000000000000000000110100000000000000000000000000001100100000000000000000000000000011000 !
b11011000000000000000000000000000110100000000000000000000000000001100100000000000000000000000000011000 &
1#
#206
b111 "
b111 %
0#
#207
b11111000000000000000000000000000111100000000000000000000000000001110100000000000000000000000000011100 !
b11111000000000000000000000000000111100000000000000000000000000001110100000000000000000000000000011100 &
1#
#208
b1000 "
b1000 %
0#
#209
b100011000000000000000000000000001000100000000000000000000000000010000100000000000000000000000000100000 !
b100011000000000000000000000000001000100000000000000000000000000010000100000000000000000000000000100000 &
1#
#210
b1001 "
b1001 %
0#
